mir/frelia/__init__.py
mir/frelia/atom.py
mir/frelia/fs.py
mir/frelia/page.py
mir/frelia/sitemap.py
mir/frelia/task.py
mir/frelia/document/__init__.py
mir/frelia/document/document.py
mir/frelia/document/enja.py
mir/frelia/document/jinja.py
mir/frelia/transforms/__init__.py
mir/frelia/transforms/document.py
mir/frelia/transforms/generic.py
mir/frelia/transforms/page.py
mir.frelia-0.1.0.dist-info/DESCRIPTION.rst
mir.frelia-0.1.0.dist-info/METADATA
mir.frelia-0.1.0.dist-info/RECORD
mir.frelia-0.1.0.dist-info/WHEEL
mir.frelia-0.1.0.dist-info/metadata.json
mir.frelia-0.1.0.dist-info/top_level.txt
