Metadata-Version: 2.0
Name: mir.frelia
Version: 0.1.0
Summary: Statis website generator library.
Home-page: https://github.com/darkfeline/mir.frelia
Author: Allen Li
Author-email: darkfeline@felesatra.moe
License: UNKNOWN
Platform: UNKNOWN
Classifier: Development Status :: 3 - Alpha
Classifier: Environment :: Console
Classifier: Intended Audience :: Developers
Classifier: Programming Language :: Python :: 3.5
